pyeye/__init__.py
pyeye-0.0.1.dist-info/LICENSE
pyeye-0.0.1.dist-info/METADATA
pyeye-0.0.1.dist-info/WHEEL
pyeye-0.0.1.dist-info/top_level.txt
pyeye-0.0.1.dist-info/RECORD
